coopr.pysp-3.5.5-py2.7-nspkg.pth
coopr/pysp/__init__.py
coopr/pysp/computeconf.py
coopr/pysp/convergence.py
coopr/pysp/drive_lagrangian_cc.py
coopr/pysp/dualphmodel.py
coopr/pysp/ef.py
coopr/pysp/ef_vss.py
coopr/pysp/ef_writer_script.py
coopr/pysp/generators.py
coopr/pysp/lagrangeMorePR.py
coopr/pysp/lagrangeParam.py
coopr/pysp/lagrangeutils.py
coopr/pysp/log_config.py
coopr/pysp/ph.py
coopr/pysp/phextension.py
coopr/pysp/phinit.py
coopr/pysp/phobjective.py
coopr/pysp/phsolverserver.py
coopr/pysp/phsolverserverutils.py
coopr/pysp/phutils.py
coopr/pysp/scenariotree.py
coopr/pysp/solutionwriter.py
coopr/pysp/plugins/__init__.py
coopr/pysp/plugins/convexhullboundextension.py
coopr/pysp/plugins/csvsolutionwriter.py
coopr/pysp/plugins/examplephextension.py
coopr/pysp/plugins/jsonsolutionwriter.py
coopr/pysp/plugins/phboundextension.py
coopr/pysp/plugins/phhistoryextension.py
coopr/pysp/plugins/schuripwriter.py
coopr/pysp/plugins/sorgw.py
coopr/pysp/plugins/testphextension.py
coopr/pysp/plugins/wwphextension.py
coopr/pysp/tests/__init__.py
coopr/pysp/tests/examples/__init__.py
coopr/pysp/tests/examples/ef_checker.py
coopr/pysp/tests/examples/ph_checker.py
coopr/pysp/tests/examples/test_ef.py
coopr/pysp/tests/examples/test_ph.py
coopr/pysp/tests/unit/__init__.py
coopr/pysp/tests/unit/test_ph.py
coopr/pysp/util/__init__.py
coopr/pysp/util/scenariomodels.py
coopr.pysp-3.5.5.dist-info/DESCRIPTION.rst
coopr.pysp-3.5.5.dist-info/entry_points.txt
coopr.pysp-3.5.5.dist-info/METADATA
coopr.pysp-3.5.5.dist-info/metadata.json
coopr.pysp-3.5.5.dist-info/namespace_packages.txt
coopr.pysp-3.5.5.dist-info/RECORD
coopr.pysp-3.5.5.dist-info/top_level.txt
coopr.pysp-3.5.5.dist-info/WHEEL
